piszkespipe/CCF.cpython-37m-darwin.so
piszkespipe/Marsh.cpython-37m-darwin.so
piszkespipe/__init__.py
piszkespipe/piszkespipe.py
piszkespipe/piszkesutils.py
piszkespipe/version.py
piszkespipe/Correlation/__init__.py
piszkespipe/Correlation/anchos40000.dat
piszkespipe/Correlation/anchos50000.dat
piszkespipe/Correlation/anchos60000.dat
piszkespipe/Correlation/correlation.py
piszkespipe/Correlation/lines.dat
piszkespipe/Correlation/lines2.dat
piszkespipe/Correlation/test.py
piszkespipe/Correlation/vels.py
piszkespipe/GLOBALutils/GLOBALutils.py
piszkespipe/GLOBALutils/__init__.py
piszkespipe/data/xc_masks/G2.mas
piszkespipe/data/xc_masks/K5.mas
piszkespipe/data/xc_masks/M2.mas
piszkespipe/wavcals/order00.dat
piszkespipe/wavcals/order01.dat
piszkespipe/wavcals/order02.dat
piszkespipe/wavcals/order03.dat
piszkespipe/wavcals/order04.dat
piszkespipe/wavcals/order05.dat
piszkespipe/wavcals/order06.dat
piszkespipe/wavcals/order07.dat
piszkespipe/wavcals/order08.dat
piszkespipe/wavcals/order09.dat
piszkespipe/wavcals/order10.dat
piszkespipe/wavcals/order11.dat
piszkespipe/wavcals/order12.dat
piszkespipe/wavcals/order13.dat
piszkespipe/wavcals/order14.dat
piszkespipe/wavcals/order15.dat
piszkespipe/wavcals/order16.dat
piszkespipe/wavcals/order17.dat
piszkespipe/wavcals/order18.dat
piszkespipe/wavcals/order19.dat
piszkespipe/wavcals/order20.dat
piszkespipe/wavcals/order21.dat
piszkespipe/wavcals/order22.dat
piszkespipe/wavcals/order23.dat
piszkespipe/wavcals/order24.dat
piszkespipe/wavcals/order25.dat
piszkespipe-0.4.1-py3.7.egg-info/PKG-INFO
piszkespipe-0.4.1-py3.7.egg-info/SOURCES.txt
piszkespipe-0.4.1-py3.7.egg-info/dependency_links.txt
piszkespipe-0.4.1-py3.7.egg-info/entry_points.txt
piszkespipe-0.4.1-py3.7.egg-info/requires.txt
piszkespipe-0.4.1-py3.7.egg-info/top_level.txt
piszkespipe-0.4.2.dist-info/LICENCE
piszkespipe-0.4.2.dist-info/METADATA
piszkespipe-0.4.2.dist-info/WHEEL
piszkespipe-0.4.2.dist-info/entry_points.txt
piszkespipe-0.4.2.dist-info/top_level.txt
piszkespipe-0.4.2.dist-info/RECORD
