Metadata-Version: 2.1
Name: piszkespipe
Version: 0.4.2
Summary: A pipeline for reducing echelle spectra obtained in Piszkesteto.
Home-page: https://github.com/astrobatty/piszkespipe/
Author: Attila Bodi
Author-email: astrobatty@gmail.com
License: UNKNOWN
Platform: UNKNOWN
Classifier: Intended Audience :: Science/Research
Classifier: Topic :: Scientific/Engineering :: Astronomy
Classifier: Development Status :: 5 - Production/Stable
Classifier: License :: OSI Approved :: GNU General Public License v3 (GPLv3)
Classifier: Operating System :: OS Independent
Classifier: Programming Language :: Python
Requires-Dist: numpy (>=1.11)
Requires-Dist: scipy (>=0.19.0)
Requires-Dist: matplotlib
Requires-Dist: ephem
Requires-Dist: skyfield
Requires-Dist: astropy
Requires-Dist: scipy
Requires-Dist: ccdproc (<2.4)
Requires-Dist: statsmodels
Requires-Dist: numba
Requires-Dist: joblib
Requires-Dist: requests
Requires-Dist: astroquery
Requires-Dist: cython
